expts/__init__.py
expts/dataset_benchmark.py
expts/debug_yaml.py
expts/main_run_get_fingerprints.py
expts/main_run_multitask.py
expts/main_run_predict.py
expts/main_run_test.py
expts/run_validation_test.py
expts/configs/config_gps_10M_pcqm4m.yaml
expts/configs/config_gps_10M_pcqm4m_mod.yaml
expts/configs/config_mpnn_10M_b3lyp.yaml
expts/configs/config_mpnn_pcqm4m.yaml
expts/data/micro_zinc_splits.csv
expts/data/tiny_zinc_splits.csv
expts/hydra-configs/README.md
expts/hydra-configs/__init__.py
expts/hydra-configs/main.yaml
expts/hydra-configs/accelerator/cpu.yaml
expts/hydra-configs/accelerator/gpu.yaml
expts/hydra-configs/accelerator/ipu.yaml
expts/hydra-configs/accelerator/ipu_pipeline.yaml
expts/hydra-configs/architecture/largemix.yaml
expts/hydra-configs/architecture/pcqm4m.yaml
expts/hydra-configs/architecture/toymix.yaml
expts/hydra-configs/experiment/toymix_mpnn.yaml
expts/hydra-configs/finetuning/admet.yaml
expts/hydra-configs/finetuning/admet_baseline.yaml
expts/hydra-configs/hparam_search/optuna.yaml
expts/hydra-configs/model/gated_gcn.yaml
expts/hydra-configs/model/gcn.yaml
expts/hydra-configs/model/gin.yaml
expts/hydra-configs/model/gine.yaml
expts/hydra-configs/model/gpspp.yaml
expts/hydra-configs/model/mpnn.yaml
expts/hydra-configs/tasks/admet.yaml
expts/hydra-configs/tasks/l1000_mcf7.yaml
expts/hydra-configs/tasks/l1000_vcap.yaml
expts/hydra-configs/tasks/largemix.yaml
expts/hydra-configs/tasks/pcba_1328.yaml
expts/hydra-configs/tasks/pcqm4m.yaml
expts/hydra-configs/tasks/pcqm4m_g25.yaml
expts/hydra-configs/tasks/pcqm4m_n4.yaml
expts/hydra-configs/tasks/toymix.yaml
expts/hydra-configs/tasks/loss_metrics_datamodule/admet.yaml
expts/hydra-configs/tasks/loss_metrics_datamodule/l1000_mcf7.yaml
expts/hydra-configs/tasks/loss_metrics_datamodule/l1000_vcap.yaml
expts/hydra-configs/tasks/loss_metrics_datamodule/largemix.yaml
expts/hydra-configs/tasks/loss_metrics_datamodule/pcba_1328.yaml
expts/hydra-configs/tasks/loss_metrics_datamodule/pcqm4m.yaml
syntheseus_graphium-0.1.0.dist-info/licenses/LICENSE
syntheseus_graphium-0.1.0.dist-info/METADATA
syntheseus_graphium-0.1.0.dist-info/WHEEL
syntheseus_graphium-0.1.0.dist-info/entry_points.txt
syntheseus_graphium-0.1.0.dist-info/top_level.txt
syntheseus_graphium-0.1.0.dist-info/RECORD
