Metadata-Version: 2.4
Name: syntheseus-graphium
Version: 0.1.0
Summary: Fork of the graphium library
Author-email: Dominique Beaini <dominique@valencediscovery.com>
Project-URL: Repository, https://github.com/kmaziarz/graphium
Classifier: Development Status :: 5 - Production/Stable
Classifier: Intended Audience :: Developers
Classifier: Intended Audience :: Healthcare Industry
Classifier: Intended Audience :: Science/Research
Classifier: Topic :: Scientific/Engineering :: Artificial Intelligence
Classifier: Topic :: Scientific/Engineering :: Bio-Informatics
Classifier: Topic :: Scientific/Engineering :: Information Analysis
Classifier: Topic :: Scientific/Engineering :: Medical Science Apps.
Classifier: Natural Language :: English
Classifier: Operating System :: OS Independent
Classifier: Programming Language :: Python
Classifier: Programming Language :: Python :: 3
Classifier: Programming Language :: Python :: 3.8
Classifier: Programming Language :: Python :: 3.9
Classifier: Programming Language :: Python :: 3.10
Classifier: Programming Language :: Python :: 3.11
Requires-Python: >=3.8
License-File: LICENSE
Requires-Dist: typer
Requires-Dist: loguru
Requires-Dist: omegaconf>=2.0.0
Requires-Dist: tqdm
Requires-Dist: platformdirs
Requires-Dist: numpy
Requires-Dist: scipy>=1.4
Requires-Dist: pandas>=1.0
Requires-Dist: scikit-learn
Requires-Dist: fastparquet
Requires-Dist: matplotlib>=3.0.1
Requires-Dist: seaborn
Requires-Dist: fsspec>=2021.6
Requires-Dist: s3fs>=2021.6
Requires-Dist: gcsfs>=2021.6
Requires-Dist: lightning>=2.0
Requires-Dist: torchmetrics<0.11,>=0.7.0
Requires-Dist: ogb
Requires-Dist: torch-geometric>=2.0
Requires-Dist: wandb
Requires-Dist: mup
Requires-Dist: torch_sparse>=0.6
Requires-Dist: torch_cluster>=1.5
Requires-Dist: torch_scatter>=2.0
Requires-Dist: datamol>=0.10
Dynamic: license-file
